README.txt
setup.py
collective/__init__.py
collective.collage.ploneformgen.egg-info/PKG-INFO
collective.collage.ploneformgen.egg-info/SOURCES.txt
collective.collage.ploneformgen.egg-info/dependency_links.txt
collective.collage.ploneformgen.egg-info/namespace_packages.txt
collective.collage.ploneformgen.egg-info/not-zip-safe
collective.collage.ploneformgen.egg-info/requires.txt
collective.collage.ploneformgen.egg-info/top_level.txt
collective/collage/__init__.py
collective/collage/ploneformgen/__init__.py
collective/collage/ploneformgen/browser.py
collective/collage/ploneformgen/configure.zcml
collective/collage/ploneformgen/templates/ploneformgen_form_standard.pt
collective/collage/ploneformgen/templates/ploneformgen_thankspage_standard.pt