Metadata-Version: 1.0
Name: collective.collage.ploneformgen
Version: 1.0a1
Summary: Add-on that allows displaying PloneFormGen-forms inside a Collage.
Home-page: http://www.plone.org/products/collective.collage.ploneformgen
Author: Malthe Borch
Author-email: mborch@gmail.com
License: GPL
Keywords: collage plone rss ploneformgen
Platform: UNKNOWN
Classifier: Programming Language :: Python
Classifier: Framework :: Plone
Classifier: License :: OSI Approved :: GNU General Public License (GPL)
Classifier: Development Status :: 5 - Production/Stable
